LICENSE
MANIFEST.in
README.rst
requirements.txt
setup.cfg
setup.py
deepsignal2/__init__.py
deepsignal2/call_modifications.py
deepsignal2/dataloader.py
deepsignal2/deepsignal2.py
deepsignal2/extract_features.py
deepsignal2/models.py
deepsignal2/train.py
deepsignal2.egg-info/PKG-INFO
deepsignal2.egg-info/SOURCES.txt
deepsignal2.egg-info/dependency_links.txt
deepsignal2.egg-info/entry_points.txt
deepsignal2.egg-info/not-zip-safe
deepsignal2.egg-info/requires.txt
deepsignal2.egg-info/top_level.txt
deepsignal2/utils/__init__.py
deepsignal2/utils/constants_torch.py
deepsignal2/utils/process_utils.py
deepsignal2/utils/ref_reader.py